README.md
setup.cfg
setup.py
requirements/all.txt
requirements/dev.txt
requirements/install.txt
s3prl/__init__.py
s3prl/hub.py
s3prl/main.py
s3prl/optimizers.py
s3prl/run_downstream.py
s3prl/run_pretrain.py
s3prl/schedulers.py
s3prl/version.txt
s3prl.egg-info/PKG-INFO
s3prl.egg-info/SOURCES.txt
s3prl.egg-info/dependency_links.txt
s3prl.egg-info/entry_points.txt
s3prl.egg-info/requires.txt
s3prl.egg-info/top_level.txt
s3prl/dataio/__init__.py
s3prl/dataio/collate_fn.py
s3prl/dataio/corpus/__init__.py
s3prl/dataio/corpus/base.py
s3prl/dataio/corpus/fluent_speech_commands.py
s3prl/dataio/corpus/iemocap.py
s3prl/dataio/corpus/librilight.py
s3prl/dataio/corpus/librispeech.py
s3prl/dataio/corpus/quesst14.py
s3prl/dataio/corpus/snips.py
s3prl/dataio/corpus/speech_commands.py
s3prl/dataio/corpus/voxceleb1sid.py
s3prl/dataio/corpus/voxceleb1sv.py
s3prl/dataio/dataset/__init__.py
s3prl/dataio/dataset/base.py
s3prl/dataio/dataset/diarization.py
s3prl/dataio/dataset/encode.py
s3prl/dataio/dataset/frame_label.py
s3prl/dataio/dataset/load_audio.py
s3prl/dataio/dataset/util.py
s3prl/dataio/encoder/__init__.py
s3prl/dataio/encoder/category.py
s3prl/dataio/encoder/g2p.py
s3prl/dataio/encoder/tokenizer.py
s3prl/dataio/encoder/vocabulary.py
s3prl/dataio/sampler/__init__.py
s3prl/dataio/sampler/balanced_weighted_sampler.py
s3prl/dataio/sampler/distributed_sampler.py
s3prl/dataio/sampler/fixed_batch_size_batch_sampler.py
s3prl/dataio/sampler/group_same_item_sampler.py
s3prl/dataio/sampler/max_timestamp_batch_sampler.py
s3prl/dataio/sampler/sorted_sampler.py
s3prl/dataset/__init__.py
s3prl/dataset/autoregressive_prediction_pipes.py
s3prl/dataset/base.py
s3prl/dataset/chunking.py
s3prl/dataset/common_pipes.py
s3prl/dataset/extract_feat_pipes.py
s3prl/dataset/hear_timestamp.py
s3prl/dataset/masked_reconstruction_pipes.py
s3prl/dataset/multiclass_tagging.py
s3prl/dataset/noise_augmentation_pipes.py
s3prl/dataset/norm_wav_pipes.py
s3prl/dataset/pretrain_apc_pipe.py
s3prl/dataset/pretrain_audioalbert_pipe.py
s3prl/dataset/pretrain_mockingjay_pipe.py
s3prl/dataset/pretrain_npc_pipe.py
s3prl/dataset/pretrain_tera_pipe.py
s3prl/dataset/speaker_verification_pipe.py
