Metadata-Version: 2.1
Name: s3prl
Version: 0.4.11
Summary: Self-Supervised Speech Pre-training and Representation Learning Toolkit
Home-page: https://github.com/s3prl/s3prl
Author: Shu-wen (Leo) Yang, Andy T. Liu (Ting-Wei Liu), and the S3PRL Team
Author-email: leo19941227@gmail.com, liuandyt@gmail.com
License: Apache Software License
Project-URL: Bug Reports, https://github.com/s3prl/s3prl/issues
Project-URL: Source, https://github.com/s3prl/s3prl/
Keywords: deep learning,speech,self-supervised,representation,pretraining
Classifier: Development Status :: 3 - Alpha
Classifier: License :: OSI Approved :: Apache Software License
Classifier: Intended Audience :: Science/Research
Classifier: Topic :: Software Development :: Libraries :: Python Modules
Classifier: Programming Language :: Python :: 3
Requires-Python: >=3.6, <4
Requires-Dist: torchaudio>=0.8.0
Requires-Dist: torch!=1.10.0,>=1.8.0
Requires-Dist: tqdm>=4.56.0
Requires-Dist: numpy>=1.21
Requires-Dist: PyYAML>=5.4.1
Requires-Dist: filelock
Requires-Dist: omegaconf>=2.1.1
Requires-Dist: setuptools>=65.5.1
Requires-Dist: requests
Requires-Dist: transformers
Requires-Dist: protobuf==3.20.3
Provides-Extra: all
Requires-Dist: joblib>=0.12.4; extra == "all"
Requires-Dist: librosa>=0.7.2; extra == "all"
Requires-Dist: scipy>=1.5.4; extra == "all"
Requires-Dist: scikit-learn>=0.23.2; extra == "all"
Requires-Dist: pandas>=1.1.5; extra == "all"
Requires-Dist: matplotlib>=3.3.4; extra == "all"
Requires-Dist: Pillow>=6.2.2; extra == "all"
Requires-Dist: numba>=0.48; extra == "all"
Requires-Dist: cython>=0.29.21; extra == "all"
Requires-Dist: packaging>=20.9; extra == "all"
Requires-Dist: transformers<5.0,>=4.10.0; extra == "all"
Requires-Dist: dtw-python==1.3.0; extra == "all"
Requires-Dist: asteroid==0.4.4; extra == "all"
Requires-Dist: sacrebleu>=2.0.0; extra == "all"
Requires-Dist: h5py; extra == "all"
Requires-Dist: sox; extra == "all"
Requires-Dist: tabulate; extra == "all"
Requires-Dist: intervaltree; extra == "all"
Requires-Dist: lxml; extra == "all"
Requires-Dist: soundfile; extra == "all"
Requires-Dist: pysndfx; extra == "all"
Requires-Dist: nltk; extra == "all"
Requires-Dist: normalise; extra == "all"
Requires-Dist: editdistance; extra == "all"
Requires-Dist: easydict; extra == "all"
Requires-Dist: catalyst; extra == "all"
Requires-Dist: sentencepiece; extra == "all"
Requires-Dist: huggingface_hub>=0.2.1; extra == "all"
Requires-Dist: mutagen; extra == "all"
Requires-Dist: pydantic; extra == "all"
Requires-Dist: sed_eval; extra == "all"
Requires-Dist: more_itertools; extra == "all"
Requires-Dist: tensorboard; extra == "all"
Provides-Extra: dev
Requires-Dist: joblib>=0.12.4; extra == "dev"
Requires-Dist: librosa>=0.7.2; extra == "dev"
Requires-Dist: scipy>=1.5.4; extra == "dev"
Requires-Dist: scikit-learn>=0.23.2; extra == "dev"
Requires-Dist: pandas>=1.1.5; extra == "dev"
Requires-Dist: matplotlib>=3.3.4; extra == "dev"
Requires-Dist: Pillow>=6.2.2; extra == "dev"
Requires-Dist: numba>=0.48; extra == "dev"
Requires-Dist: cython>=0.29.21; extra == "dev"
Requires-Dist: packaging>=20.9; extra == "dev"
Requires-Dist: transformers<5.0,>=4.10.0; extra == "dev"
Requires-Dist: dtw-python==1.3.0; extra == "dev"
Requires-Dist: asteroid==0.4.4; extra == "dev"
Requires-Dist: sacrebleu>=2.0.0; extra == "dev"
Requires-Dist: h5py; extra == "dev"
Requires-Dist: sox; extra == "dev"
Requires-Dist: tabulate; extra == "dev"
Requires-Dist: intervaltree; extra == "dev"
Requires-Dist: lxml; extra == "dev"
Requires-Dist: soundfile; extra == "dev"
Requires-Dist: pysndfx; extra == "dev"
Requires-Dist: nltk; extra == "dev"
Requires-Dist: normalise; extra == "dev"
Requires-Dist: editdistance; extra == "dev"
Requires-Dist: easydict; extra == "dev"
Requires-Dist: catalyst; extra == "dev"
Requires-Dist: sentencepiece; extra == "dev"
Requires-Dist: huggingface_hub>=0.2.1; extra == "dev"
Requires-Dist: mutagen; extra == "dev"
Requires-Dist: pydantic; extra == "dev"
Requires-Dist: sed_eval; extra == "dev"
Requires-Dist: more_itertools; extra == "dev"
Requires-Dist: tensorboard; extra == "dev"
Requires-Dist: python-dotenv; extra == "dev"
Requires-Dist: pytest; extra == "dev"
Requires-Dist: pytest-xdist; extra == "dev"
Requires-Dist: tox; extra == "dev"
Requires-Dist: pre-commit; extra == "dev"
Requires-Dist: flake8==3.9.2; extra == "dev"
Requires-Dist: black==22.3.0; extra == "dev"
Requires-Dist: isort==5.10.1; extra == "dev"
Requires-Dist: sphinx==5.1.1; extra == "dev"
Requires-Dist: furo; extra == "dev"
Requires-Dist: importlib_metadata<5.0; extra == "dev"
